librapid/VERSION.hpp
librapid/__init__.py
librapid/_librapid.cp310-win_amd64.pyd
librapid/librapid.hpp
librapid/array/array.hpp
librapid/array/arrayBase.hpp
librapid/array/cast.hpp
librapid/array/commaInitializer.hpp
librapid/array/cwisebinop.hpp
librapid/array/cwiseunop.hpp
librapid/array/denseStorage.hpp
librapid/array/traits.hpp
librapid/array/valueReference.hpp
librapid/array/functors/assignOp.hpp
librapid/array/functors/functors.hpp
librapid/array/functors/binary/binary.hpp
librapid/array/functors/binary/bitwise.hpp
librapid/array/functors/binary/scalarArithmetic.hpp
librapid/array/functors/matrix/transpose.hpp
librapid/array/functors/unary/negate.hpp
librapid/array/functors/unary/unary.hpp
librapid/array/helpers/extendedTypes.hpp
librapid/array/helpers/extent.hpp
librapid/array/helpers/kernelFormat.hpp
librapid/array/helpers/kernelHelper.hpp
librapid/blas/cblas.h
librapid/blas/f77blas.h
librapid/blas/lapack.h
librapid/blas/lapacke.h
librapid/blas/lapacke_config.h
librapid/blas/lapacke_example_aux.h
librapid/blas/lapacke_mangling.h
librapid/blas/lapacke_utils.h
librapid/blas/openblas.dll
librapid/blas/openblas.lib
librapid/blas/openblas_config.h
librapid/cuda/cudaCodeLoader.hpp
librapid/cuda/exception.h
librapid/cuda/helper_cuda.h
librapid/cuda/helper_cuda_drvapi.h
librapid/cuda/helper_cusolver.h
librapid/cuda/helper_functions.h
librapid/cuda/helper_image.h
librapid/cuda/helper_math.h
librapid/cuda/helper_multiprocess.h
librapid/cuda/helper_string.h
librapid/cuda/helper_timer.h
librapid/cuda/kernel_header.h
librapid/cuda/memUtils.hpp
librapid/cuda/nvrtc_helper.h
librapid/include/Vc/Allocator
librapid/include/Vc/IO
librapid/include/Vc/Memory
librapid/include/Vc/SimdArray
librapid/include/Vc/Utils
librapid/include/Vc/Vc
librapid/include/Vc/algorithm
librapid/include/Vc/array
librapid/include/Vc/cpuid.h
librapid/include/Vc/fwddecl.h
librapid/include/Vc/global.h
librapid/include/Vc/iterators
librapid/include/Vc/limits
librapid/include/Vc/simdize
librapid_cuda_11.5.0-0.4.6.dist-info/LICENSE
librapid_cuda_11.5.0-0.4.6.dist-info/METADATA
librapid_cuda_11.5.0-0.4.6.dist-info/WHEEL
librapid_cuda_11.5.0-0.4.6.dist-info/top_level.txt
librapid_cuda_11.5.0-0.4.6.dist-info/RECORD
